GeocodingCHN/Geocoding.py
GeocodingCHN/__init__.py
GeocodingCHN/geocoding.jar
GeocodingCHN/model/__init__.py
GeocodingCHN/model/address.py
GeocodingCHN/model/document.py
GeocodingCHN/model/matched.py
GeocodingCHN/model/region_type.py
GeocodingCHN/model/term.py
GeocodingCHN/model/version.py
GeocodingCHN-1.4.5.dist-info/LICENSE
GeocodingCHN-1.4.5.dist-info/METADATA
GeocodingCHN-1.4.5.dist-info/WHEEL
GeocodingCHN-1.4.5.dist-info/top_level.txt
GeocodingCHN-1.4.5.dist-info/RECORD
