Metadata-Version: 2.1
Name: GeocodingCHN
Version: 1.4.5
Summary: 地址标准化
Home-page: https://github.com/casuallyName/Geocoding
Author: ZhouHang
Author-email: fjkl@vip.qq.com
License: MIT Licence
Classifier: Programming Language :: Python :: 3
Classifier: License :: OSI Approved :: MIT License
Classifier: Operating System :: OS Independent
Requires-Python: >=3.7
License-File: LICENSE
Requires-Dist: jpype1
